PaperBee/__init__.py
PaperBee/daily_posting.py
PaperBee/papers/__init__.py
PaperBee/papers/cli.py
PaperBee/papers/google_sheet.py
PaperBee/papers/llm_filtering.py
PaperBee/papers/mattermost_papers_formatter.py
PaperBee/papers/papers_finder.py
PaperBee/papers/posting_required_params.py
PaperBee/papers/slack_papers_formatter.py
PaperBee/papers/telegram_papers_formatter.py
PaperBee/papers/utils.py
PaperBee/papers/validate_inputs.py
PaperBee/papers/zulip_papers_formatter.py
paperbee-1.2.1.dist-info/METADATA
paperbee-1.2.1.dist-info/WHEEL
paperbee-1.2.1.dist-info/entry_points.txt
paperbee-1.2.1.dist-info/licenses/LICENSE
paperbee-1.2.1.dist-info/RECORD
