Metadata-Version: 2.4
Name: PaperBee
Version: 1.2.1
Summary: 
License-File: LICENSE
Author: Daniele Lucarelli
Author-email: daniele.lucarelli@tum.de
Requires-Python: >=3.10,<4.0
Classifier: Programming Language :: Python :: 3
Classifier: Programming Language :: Python :: 3.10
Classifier: Programming Language :: Python :: 3.11
Classifier: Programming Language :: Python :: 3.12
Classifier: Programming Language :: Python :: 3.13
Classifier: Programming Language :: Python :: 3.14
Requires-Dist: defusedxml (>=0.7.1,<0.8.0)
Requires-Dist: findpapers (==0.6.7)
Requires-Dist: gspread (==6.0.2)
Requires-Dist: mattermostdriver (>=7.3.0,<8.0.0)
Requires-Dist: oauth2client (==4.1.3)
Requires-Dist: ollama (==0.4.6)
Requires-Dist: openai (==1.50.2)
Requires-Dist: pandas (==2.2.3)
Requires-Dist: python-editor (==1.0.4)
Requires-Dist: python-telegram-bot (==21.1.1)
Requires-Dist: pyyaml (==6.0.2)
Requires-Dist: slack-bolt (==1.18.1)
Requires-Dist: slack_sdk (==3.27.1)
Requires-Dist: zulip (==0.9.0)
Project-URL: Documentation, https://github.com/theislab/paperbee
Project-URL: Repository, https://github.com/theislab/paperbee
